Metadata-Version: 2.1
Name: kenu-ai-dev
Version: 0.0.1
Summary: Python Chat AI
Author: r4isy
Author-email: r4isy@kenucheck.xyz
